{"trial_id": "19", "hyperparameters": {"space": [{"class_name": "Int", "config": {"name": "input_lstm_layer", "default": null, "conditions": [], "min_value": 50, "max_value": 500, "step": 50, "sampling": null}}, {"class_name": "Int", "config": {"name": "final_lstm_layer", "default": null, "conditions": [], "min_value": 50, "max_value": 500, "step": 50, "sampling": null}}, {"class_name": "Float", "config": {"name": "Dropout_rate", "default": 0.0, "conditions": [], "min_value": 0.0, "max_value": 0.5, "step": 0.1, "sampling": null}}, {"class_name": "Choice", "config": {"name": "dense_activation", "default": "sigmoid", "conditions": [], "values": ["sigmoid"], "ordered": false}}], "values": {"input_lstm_layer": 350, "final_lstm_layer": 350, "Dropout_rate": 0.30000000000000004, "dense_activation": "sigmoid"}}, "metrics": {"metrics": {"loss": {"direction": "min", "observations": [{"value": [0.007146803662180901], "step": 132}]}, "mse": {"direction": "min", "observations": [{"value": [0.007146803662180901], "step": 132}]}, "val_loss": {"direction": "min", "observations": [{"value": [0.006270278245210648], "step": 132}]}, "val_mse": {"direction": "min", "observations": [{"value": [0.006270278245210648], "step": 132}]}}}, "score": 0.007146803662180901, "best_step": 132, "status": "COMPLETED"}